[
  {
    "nameEnglish": "The Book of Faith",
    "nameBengali": "১/ কিতাবুল ঈমান",
    "lastUpdate": "2015-05-13",
    "isActive": "1",
    "id": "2",
    "chSerial": "1",
    "bookId": "2",
    "hadith_number": "426",
    "range_start": "1",
    "range_end": "426",
    "bookInitial": "muslim"
  },
  {
    "nameEnglish": "2/ The Book of Purification ",
    "nameBengali": "২/ তাহারাত (পবিত্রতা)",
    "lastUpdate": "2015-05-13",
    "isActive": "1",
    "id": "92",
    "chSerial": "2",
    "bookId": "2",
    "hadith_number": "145",
    "range_start": "427",
    "range_end": "571",
    "bookInitial": "muslim"
  },
  {
    "nameEnglish": "3/ The Book of Menstruation",
    "nameBengali": "৩/ হায়েয",
    "lastUpdate": "2015-05-13",
    "isActive": "1",
    "id": "93",
    "chSerial": "3",
    "bookId": "2",
    "hadith_number": "151",
    "range_start": "572",
    "range_end": "722",
    "bookInitial": "muslim"
  },
  {
    "nameEnglish": "4/ The Book of Prayers",
    "nameBengali": "৪/ কিতাবুস স্বলাত",
    "lastUpdate": "2015-05-13",
    "isActive": "1",
    "id": "94",
    "chSerial": "4",
    "bookId": "2",
    "hadith_number": "323",
    "range_start": "723",
    "range_end": "1043",
    "bookInitial": "muslim"
  },
  {
    "nameEnglish": "5/ Mosque & Place of Salah",
    "nameBengali": "৫/ মসজিদ ও সালাতের স্থান",
    "lastUpdate": "2015-05-13",
    "isActive": "1",
    "id": "96",
    "chSerial": "5",
    "bookId": "2",
    "hadith_number": "399",
    "range_start": "1044",
    "range_end": "1442",
    "bookInitial": "muslim"
  },
  {
    "nameEnglish": "6/ The Book of Prayer - Travellers ",
    "nameBengali": "৬/ মুসাফিরের সালাত ও কসর",
    "lastUpdate": "2015-05-13",
    "isActive": "1",
    "id": "103",
    "chSerial": "6",
    "bookId": "2",
    "hadith_number": "267",
    "range_start": "1443",
    "range_end": "1709",
    "bookInitial": "muslim"
  },
  {
    "nameEnglish": "7/ Fadayalul Quran",
    "nameBengali": "৭/ ফাযাইলুল কুরআন",
    "lastUpdate": "2015-05-13",
    "isActive": "1",
    "id": "107",
    "chSerial": "7",
    "bookId": "2",
    "hadith_number": "114",
    "range_start": "1710",
    "range_end": "1823",
    "bookInitial": "muslim"
  },
  {
    "nameEnglish": "8/ Jumu'a",
    "nameBengali": "৮/ জুমু’আ",
    "lastUpdate": "2015-05-13",
    "isActive": "1",
    "id": "108",
    "chSerial": "8",
    "bookId": "2",
    "hadith_number": "93",
    "range_start": "1824",
    "range_end": "1916",
    "bookInitial": "muslim"
  },
  {
    "nameEnglish": "9/ Salat of Two EID",
    "nameBengali": "৯/ দুই ঈদের সালাত",
    "lastUpdate": "2015-05-13",
    "isActive": "1",
    "id": "109",
    "chSerial": "9",
    "bookId": "2",
    "hadith_number": "26",
    "range_start": "1917",
    "range_end": "1942",
    "bookInitial": "muslim"
  },
  {
    "nameEnglish": "10/ Salat of Istiska",
    "nameBengali": "১০/ ইসতিসকার সালাত",
    "lastUpdate": "2015-05-13",
    "isActive": "1",
    "id": "110",
    "chSerial": "10",
    "bookId": "2",
    "hadith_number": "19",
    "range_start": "1943",
    "range_end": "1961",
    "bookInitial": "muslim"
  },
  {
    "nameEnglish": "11/ Salatul Kusuf",
    "nameBengali": "১১/ সালাতুল কুসূফ",
    "lastUpdate": "2015-05-13",
    "isActive": "1",
    "id": "111",
    "chSerial": "11",
    "bookId": "2",
    "hadith_number": "33",
    "range_start": "1962",
    "range_end": "1994",
    "bookInitial": "muslim"
  },
  {
    "nameEnglish": "12/ Janajah",
    "nameBengali": "১২/ জানাযা সম্পর্কিত",
    "lastUpdate": "2015-05-13",
    "isActive": "1",
    "id": "112",
    "chSerial": "12",
    "bookId": "2",
    "hadith_number": "140",
    "range_start": "1995",
    "range_end": "2134",
    "bookInitial": "muslim"
  },
  {
    "nameEnglish": "13/ Jakat",
    "nameBengali": "১৩/ যাকাত",
    "lastUpdate": "2015-05-13",
    "isActive": "1",
    "id": "113",
    "chSerial": "13",
    "bookId": "2",
    "hadith_number": "231",
    "range_start": "2135",
    "range_end": "2365",
    "bookInitial": "muslim"
  },
  {
    "nameEnglish": "14/ Fasting",
    "nameBengali": "১৪/ সিয়াম (রোজা)",
    "lastUpdate": "2015-05-13",
    "isActive": "1",
    "id": "114",
    "chSerial": "14",
    "bookId": "2",
    "hadith_number": "285",
    "range_start": "2366",
    "range_end": "2650",
    "bookInitial": "muslim"
  },
  {
    "nameEnglish": "15/ Itiquaf",
    "nameBengali": "১৫/ ইতিকাফ",
    "lastUpdate": "2015-05-13",
    "isActive": "1",
    "id": "116",
    "chSerial": "15",
    "bookId": "2",
    "hadith_number": "11",
    "range_start": "2651",
    "range_end": "2661",
    "bookInitial": "muslim"
  },
  {
    "nameEnglish": "16/ Hajj",
    "nameBengali": "১৬/ হাজ্জ",
    "lastUpdate": "2015-05-13",
    "isActive": "1",
    "id": "117",
    "chSerial": "16",
    "bookId": "2",
    "hadith_number": "606",
    "range_start": "2662",
    "range_end": "3267",
    "bookInitial": "muslim"
  },
  {
    "nameEnglish": "17/ Marriage",
    "nameBengali": "১৭/ বিবাহ",
    "lastUpdate": "2015-05-13",
    "isActive": "1",
    "id": "118",
    "chSerial": "17",
    "bookId": "2",
    "hadith_number": "169",
    "range_start": "3268",
    "range_end": "3436",
    "bookInitial": "muslim"
  },
  {
    "nameEnglish": "18/ Drinking Milk",
    "nameBengali": "১৮/ দুধপান",
    "lastUpdate": "2015-05-13",
    "isActive": "1",
    "id": "119",
    "chSerial": "18",
    "bookId": "2",
    "hadith_number": "83",
    "range_start": "3437",
    "range_end": "3519",
    "bookInitial": "muslim"
  },
  {
    "nameEnglish": "19/ Divorce",
    "nameBengali": "১৯/ তালাক",
    "lastUpdate": "2015-05-13",
    "isActive": "1",
    "id": "120",
    "chSerial": "19",
    "bookId": "2",
    "hadith_number": "85",
    "range_start": "3520",
    "range_end": "3604",
    "bookInitial": "muslim"
  },
  {
    "nameEnglish": "20/ Li'an",
    "nameBengali": "২০/ লি’আন",
    "lastUpdate": "2015-05-13",
    "isActive": "1",
    "id": "121",
    "chSerial": "20",
    "bookId": "2",
    "hadith_number": "24",
    "range_start": "3605",
    "range_end": "3628",
    "bookInitial": "muslim"
  },
  {
    "nameEnglish": "21/ Dashmukti",
    "nameBengali": "২১/ দাসমুক্তি",
    "lastUpdate": "2015-05-13",
    "isActive": "1",
    "id": "122",
    "chSerial": "21",
    "bookId": "2",
    "hadith_number": "30",
    "range_start": "3629",
    "range_end": "3658",
    "bookInitial": "muslim"
  },
  {
    "nameEnglish": "22/ Buying & Selling",
    "nameBengali": "২২/ ক্রয়-বিক্রয়",
    "lastUpdate": "2015-05-13",
    "isActive": "1",
    "id": "123",
    "chSerial": "22",
    "bookId": "2",
    "hadith_number": "159",
    "range_start": "3659",
    "range_end": "3817",
    "bookInitial": "muslim"
  },
  {
    "nameEnglish": "23/ Borga",
    "nameBengali": "২৩/ মুসাকাত ও মুযারাত (বর্গাচাষ)",
    "lastUpdate": "2015-05-13",
    "isActive": "1",
    "id": "124",
    "chSerial": "23",
    "bookId": "2",
    "hadith_number": "177",
    "range_start": "3818",
    "range_end": "3994",
    "bookInitial": "muslim"
  },
  {
    "nameEnglish": "24/ Farayaze",
    "nameBengali": "২৪/ ফারাইয (উত্তরাধিকার বণ্টনের  বিধান)",
    "lastUpdate": "2015-05-13",
    "isActive": "1",
    "id": "125",
    "chSerial": "24",
    "bookId": "2",
    "hadith_number": "23",
    "range_start": "3995",
    "range_end": "4017",
    "bookInitial": "muslim"
  },
  {
    "nameEnglish": "25/ Hiba",
    "nameBengali": "২৫/ হিবা",
    "lastUpdate": "2015-05-13",
    "isActive": "1",
    "id": "126",
    "chSerial": "25",
    "bookId": "2",
    "hadith_number": "40",
    "range_start": "4018",
    "range_end": "4057",
    "bookInitial": "muslim"
  },
  {
    "nameEnglish": "26/ Ociyat",
    "nameBengali": "২৬/ ওসিয়াত",
    "lastUpdate": "2015-05-13",
    "isActive": "1",
    "id": "127",
    "chSerial": "26",
    "bookId": "2",
    "hadith_number": "31",
    "range_start": "4058",
    "range_end": "4088",
    "bookInitial": "muslim"
  },
  {
    "nameEnglish": "27/ Manot",
    "nameBengali": "২৭/ মানত",
    "lastUpdate": "2015-05-13",
    "isActive": "1",
    "id": "128",
    "chSerial": "27",
    "bookId": "2",
    "hadith_number": "19",
    "range_start": "4089",
    "range_end": "4107",
    "bookInitial": "muslim"
  },
  {
    "nameEnglish": "28/ Kasam",
    "nameBengali": "২৮/ কসম",
    "lastUpdate": "2015-05-13",
    "isActive": "1",
    "id": "129",
    "chSerial": "28",
    "bookId": "2",
    "hadith_number": "87",
    "range_start": "4108",
    "range_end": "4194",
    "bookInitial": "muslim"
  },
  {
    "nameEnglish": "30/ Punishment",
    "nameBengali": "৩০/ অপরাধের শাস্তি",
    "lastUpdate": "2016-04-11",
    "isActive": "1",
    "id": "130",
    "chSerial": "30",
    "bookId": "2",
    "hadith_number": "70",
    "range_start": "4251",
    "range_end": "4320",
    "bookInitial": "muslim"
  },
  {
    "nameEnglish": "31/ Justice",
    "nameBengali": "৩১/ বিচার বিধান",
    "lastUpdate": "2016-04-11",
    "isActive": "1",
    "id": "131",
    "chSerial": "31",
    "bookId": "2",
    "hadith_number": "28",
    "range_start": "4321",
    "range_end": "4348",
    "bookInitial": "muslim"
  },
  {
    "nameEnglish": "32/ Lost & Found",
    "nameBengali": "৩২/ হারানো বস্তুপ্রাপ্তি",
    "lastUpdate": "2016-04-11",
    "isActive": "1",
    "id": "132",
    "chSerial": "32",
    "bookId": "2",
    "hadith_number": "21",
    "range_start": "4349",
    "range_end": "4369",
    "bookInitial": "muslim"
  },
  {
    "nameEnglish": "33/ Zihad",
    "nameBengali": "৩৩/ জিহাদ ও এর নীতিমালা",
    "lastUpdate": "2016-04-11",
    "isActive": "1",
    "id": "133",
    "chSerial": "33",
    "bookId": "2",
    "hadith_number": "180",
    "range_start": "4370",
    "range_end": "4549",
    "bookInitial": "muslim"
  },
  {
    "nameEnglish": "34/ Government & Rulling",
    "nameBengali": "৩৪/ রাষ্ট্রক্ষমতা ও প্রশাসন",
    "lastUpdate": "2016-04-11",
    "isActive": "1",
    "id": "134",
    "chSerial": "34",
    "bookId": "2",
    "hadith_number": "269",
    "range_start": "4550",
    "range_end": "4818",
    "bookInitial": "muslim"
  },
  {
    "nameEnglish": "35/ Hunting",
    "nameBengali": "৩৫/ শিকার ও যবেহকৃত জন্তু এবং যে সব পশুর গোশত খাওয়া হালাল ",
    "lastUpdate": "2016-04-11",
    "isActive": "1",
    "id": "135",
    "chSerial": "35",
    "bookId": "2",
    "hadith_number": "85",
    "range_start": "4819",
    "range_end": "4903",
    "bookInitial": "muslim"
  },
  {
    "nameEnglish": "36/ Secrifice",
    "nameBengali": "৩৬/ কুরবানী",
    "lastUpdate": "2016-04-11",
    "isActive": "1",
    "id": "136",
    "chSerial": "36",
    "bookId": "2",
    "hadith_number": "61",
    "range_start": "4904",
    "range_end": "4964",
    "bookInitial": "muslim"
  },
  {
    "nameEnglish": "37/ Drinks",
    "nameBengali": "৩৭/ পানীয় দ্রব্য",
    "lastUpdate": "2016-04-11",
    "isActive": "1",
    "id": "137",
    "chSerial": "37",
    "bookId": "2",
    "hadith_number": "247",
    "range_start": "4965",
    "range_end": "5211",
    "bookInitial": "muslim"
  },
  {
    "nameEnglish": "38/ Dressup",
    "nameBengali": "৩৮/ পোশাক ও সাজসজ্জা",
    "lastUpdate": "2016-04-11",
    "isActive": "1",
    "id": "138",
    "chSerial": "38",
    "bookId": "2",
    "hadith_number": "189",
    "range_start": "5212",
    "range_end": "5400",
    "bookInitial": "muslim"
  },
  {
    "nameEnglish": "39/ Courtecy",
    "nameBengali": "৩৯/ শিষ্টাচার",
    "lastUpdate": "2016-04-11",
    "isActive": "1",
    "id": "139",
    "chSerial": "39",
    "bookId": "2",
    "hadith_number": "60",
    "range_start": "5401",
    "range_end": "5460",
    "bookInitial": "muslim"
  },
  {
    "nameEnglish": "40/ Salam",
    "nameBengali": "৪০/ সালাম",
    "lastUpdate": "2016-04-11",
    "isActive": "1",
    "id": "140",
    "chSerial": "40",
    "bookId": "2",
    "hadith_number": "168",
    "range_start": "5461",
    "range_end": "5628",
    "bookInitial": "muslim"
  },
  {
    "nameEnglish": "41/ Snake Killing",
    "nameBengali": "৪১/ সাপ ইত্যাদি নিধন",
    "lastUpdate": "2016-04-11",
    "isActive": "1",
    "id": "141",
    "chSerial": "41",
    "bookId": "2",
    "hadith_number": "38",
    "range_start": "5629",
    "range_end": "5666",
    "bookInitial": "muslim"
  },
  {
    "nameEnglish": "42/ Courtecy",
    "nameBengali": "৪২/ শব্দচয়ণ ও শব্দ প্রয়োগে শিষ্টাচার",
    "lastUpdate": "2016-04-11",
    "isActive": "1",
    "id": "142",
    "chSerial": "42",
    "bookId": "2",
    "hadith_number": "22",
    "range_start": "5667",
    "range_end": "5688",
    "bookInitial": "muslim"
  },
  {
    "nameEnglish": "43/ Poem",
    "nameBengali": "৪৩/ কবিতা",
    "lastUpdate": "2016-04-11",
    "isActive": "1",
    "id": "143",
    "chSerial": "43",
    "bookId": "2",
    "hadith_number": "11",
    "range_start": "5689",
    "range_end": "5699",
    "bookInitial": "muslim"
  },
  {
    "nameEnglish": "4/ Dream",
    "nameBengali": "৪৪/ স্বপ্ন",
    "lastUpdate": "2016-04-11",
    "isActive": "1",
    "id": "144",
    "chSerial": "43",
    "bookId": "2",
    "hadith_number": "39",
    "range_start": "5700",
    "range_end": "5738",
    "bookInitial": "muslim"
  },
  {
    "nameEnglish": "45/ Results",
    "nameBengali": "৪৫/ ফযীলত",
    "lastUpdate": "2016-04-11",
    "isActive": "1",
    "id": "145",
    "chSerial": "45",
    "bookId": "2",
    "hadith_number": "214",
    "range_start": "5739",
    "range_end": "5952",
    "bookInitial": "muslim"
  },
  {
    "nameEnglish": "46/ Sahaba",
    "nameBengali": "৪৬/ সাহাবী (রাঃ) গণের ফযীলত",
    "lastUpdate": "2016-04-11",
    "isActive": "1",
    "id": "146",
    "chSerial": "46",
    "bookId": "2",
    "hadith_number": "317",
    "range_start": "5953",
    "range_end": "6283",
    "bookInitial": "muslim"
  },
  {
    "nameEnglish": "47/ Relationship",
    "nameBengali": "৪৭/ সদ্ব্যবহার, আত্নীয়তার সম্পর্ক রক্ষা ও শিষ্টাচার",
    "lastUpdate": "2016-04-11",
    "isActive": "1",
    "id": "166",
    "chSerial": "47",
    "bookId": "2",
    "hadith_number": "212",
    "range_start": "6269",
    "range_end": "6481",
    "bookInitial": "muslim"
  },
  {
    "nameEnglish": "48/ Luck",
    "nameBengali": "৪৮/ তাকদীর",
    "lastUpdate": "2016-04-11",
    "isActive": "1",
    "id": "167",
    "chSerial": "48",
    "bookId": "2",
    "hadith_number": "51",
    "range_start": "6482",
    "range_end": "6532",
    "bookInitial": "muslim"
  },
  {
    "nameEnglish": "49/ Knowledge",
    "nameBengali": "৪৯/ ইলম",
    "lastUpdate": "2016-04-11",
    "isActive": "1",
    "id": "168",
    "chSerial": "49",
    "bookId": "2",
    "hadith_number": "28",
    "range_start": "6533",
    "range_end": "6560",
    "bookInitial": "muslim"
  },
  {
    "nameEnglish": "50/ Jikr, Dua",
    "nameBengali": "৫০/ যিকর, দু’আ, তাওবা ও ইসতিগফার",
    "lastUpdate": "2016-04-11",
    "isActive": "1",
    "id": "169",
    "chSerial": "50",
    "bookId": "2",
    "hadith_number": "139",
    "range_start": "6561",
    "range_end": "6699",
    "bookInitial": "muslim"
  },
  {
    "nameEnglish": "51/ Tauba",
    "nameBengali": "৫১/ তাওবা",
    "lastUpdate": "2016-04-11",
    "isActive": "1",
    "id": "170",
    "chSerial": "51",
    "bookId": "2",
    "hadith_number": "67",
    "range_start": "6700",
    "range_end": "6766",
    "bookInitial": "muslim"
  },
  {
    "nameEnglish": "52/ Behave with the Munafique",
    "nameBengali": "৫২/ মুনাফিকদের আচরন এবং তাদের সম্পর্কে বিধান। ",
    "lastUpdate": "2016-04-11",
    "isActive": "1",
    "id": "171",
    "chSerial": "52",
    "bookId": "2",
    "hadith_number": "21",
    "range_start": "6767",
    "range_end": "6787",
    "bookInitial": "muslim"
  },
  {
    "nameEnglish": "53/ Kiyamat",
    "nameBengali": "৫৩/ কিয়ামত, জান্নাত ও জাহান্নামের বিবরণ",
    "lastUpdate": "2016-04-11",
    "isActive": "1",
    "id": "172",
    "chSerial": "53",
    "bookId": "2",
    "hadith_number": "81",
    "range_start": "6788",
    "range_end": "6868",
    "bookInitial": "muslim"
  },
  {
    "nameEnglish": "54/ Jannah",
    "nameBengali": "৫৪/ জান্নাত, জান্নাতের নিয়ামত ও জান্নাতবাসীগনের বিবরণ",
    "lastUpdate": "2016-04-11",
    "isActive": "1",
    "id": "173",
    "chSerial": "54",
    "bookId": "2",
    "hadith_number": "103",
    "range_start": "6869",
    "range_end": "7007",
    "bookInitial": "muslim"
  },
  {
    "nameEnglish": "55/ Fitna",
    "nameBengali": "৫৫/ ফিতনা সমূহ ও কিয়ামতের নিদর্শনাবলী",
    "lastUpdate": "2016-04-11",
    "isActive": "1",
    "id": "174",
    "chSerial": "55",
    "bookId": "2",
    "hadith_number": "177",
    "range_start": "6971",
    "range_end": "7148",
    "bookInitial": "muslim"
  },
  {
    "nameEnglish": "56/ Dunia",
    "nameBengali": "৫৬/ যুহুদ ও দুনিয়ার প্রতি আকর্ষণহীনতা সম্পর্কিত বর্ণনা",
    "lastUpdate": "2016-04-11",
    "isActive": "1",
    "id": "175",
    "chSerial": "56",
    "bookId": "2",
    "hadith_number": "93",
    "range_start": "7149",
    "range_end": "7241",
    "bookInitial": "muslim"
  },
  {
    "nameEnglish": "57/ Tafsir",
    "nameBengali": "৫৭/ তাফসীর",
    "lastUpdate": "2016-04-11",
    "isActive": "1",
    "id": "181",
    "chSerial": "57",
    "bookId": "2",
    "hadith_number": "40",
    "range_start": "7242",
    "range_end": "7281",
    "bookInitial": "muslim"
  },
  {
    "nameEnglish": "",
    "nameBengali": "২৯/ 'কাসামা'-(খুনের ব্যাপারে বিশেষ ধরনের হলফ করা), 'মুহারিবীন' (শত্রু সৈন্য), 'কিসাস' (খুনের বদলা) এবং 'দিয়াত' (খুনের শাস্তি স্বরূপ অর্থদন্ড)",
    "lastUpdate": "2016-04-11",
    "isActive": "1",
    "id": "513",
    "chSerial": "29",
    "bookId": "2",
    "hadith_number": "56",
    "range_start": "4195",
    "range_end": "4250",
    "bookInitial": "muslim"
  }
]
